alibabacloud_slb20140515/__init__.py
alibabacloud_slb20140515/client.py
alibabacloud_slb20140515/models/__init__.py
alibabacloud_slb20140515/models/_add_access_control_list_entry_request.py
alibabacloud_slb20140515/models/_add_access_control_list_entry_response.py
alibabacloud_slb20140515/models/_add_access_control_list_entry_response_body.py
alibabacloud_slb20140515/models/_add_backend_servers_request.py
alibabacloud_slb20140515/models/_add_backend_servers_response.py
alibabacloud_slb20140515/models/_add_backend_servers_response_body.py
alibabacloud_slb20140515/models/_add_listener_white_list_item_request.py
alibabacloud_slb20140515/models/_add_listener_white_list_item_response.py
alibabacloud_slb20140515/models/_add_listener_white_list_item_response_body.py
alibabacloud_slb20140515/models/_add_tags_request.py
alibabacloud_slb20140515/models/_add_tags_response.py
alibabacloud_slb20140515/models/_add_tags_response_body.py
alibabacloud_slb20140515/models/_add_vserver_group_backend_servers_request.py
alibabacloud_slb20140515/models/_add_vserver_group_backend_servers_response.py
alibabacloud_slb20140515/models/_add_vserver_group_backend_servers_response_body.py
alibabacloud_slb20140515/models/_create_access_control_list_request.py
alibabacloud_slb20140515/models/_create_access_control_list_response.py
alibabacloud_slb20140515/models/_create_access_control_list_response_body.py
alibabacloud_slb20140515/models/_create_domain_extension_request.py
alibabacloud_slb20140515/models/_create_domain_extension_response.py
alibabacloud_slb20140515/models/_create_domain_extension_response_body.py
alibabacloud_slb20140515/models/_create_load_balancer_httplistener_request.py
alibabacloud_slb20140515/models/_create_load_balancer_httplistener_response.py
alibabacloud_slb20140515/models/_create_load_balancer_httplistener_response_body.py
alibabacloud_slb20140515/models/_create_load_balancer_httpslistener_request.py
alibabacloud_slb20140515-3.3.30.dist-info/LICENSE
alibabacloud_slb20140515-3.3.30.dist-info/METADATA
alibabacloud_slb20140515-3.3.30.dist-info/WHEEL
alibabacloud_slb20140515-3.3.30.dist-info/top_level.txt
alibabacloud_slb20140515-3.3.30.dist-info/RECORD
